colab_everything/__init__.py
colab_everything/_modidx.py
colab_everything/core.py
colab_everything-0.0.13.dist-info/LICENSE
colab_everything-0.0.13.dist-info/METADATA
colab_everything-0.0.13.dist-info/WHEEL
colab_everything-0.0.13.dist-info/entry_points.txt
colab_everything-0.0.13.dist-info/top_level.txt
colab_everything-0.0.13.dist-info/RECORD
