Metadata-Version: 2.1
Name: colab-everything
Version: 0.0.13
Summary: Python library to run streamlit, flask, fastapi, etc on google colab.
Home-page: https://github.com/Ankur-singh/colab_everything/
Author: Ankur Singh
Author-email: as.ankursingh3.1@gmail.com
License: Apache Software License 2.0
Keywords: nbdev
Classifier: Development Status :: 3 - Alpha
Classifier: Intended Audience :: Developers
Classifier: Natural Language :: English
Classifier: Programming Language :: Python :: 3.7
Classifier: Programming Language :: Python :: 3.8
Classifier: Programming Language :: Python :: 3.9
Classifier: Programming Language :: Python :: 3.10
Classifier: License :: OSI Approved :: Apache Software License
Requires-Python: >=3.7
License-File: LICENSE
Requires-Dist: pyngrok
Requires-Dist: urllib3
Provides-Extra: dev
